accelbyte_py_sdk/api/gametelemetry/__init__.py
accelbyte_py_sdk/api/gametelemetry/errors.py
accelbyte_py_sdk/api/gametelemetry/models/__init__.py
accelbyte_py_sdk/api/gametelemetry/models/base_error_response.py
accelbyte_py_sdk/api/gametelemetry/models/get_namespace_event_response.py
accelbyte_py_sdk/api/gametelemetry/models/http_validation_error.py
accelbyte_py_sdk/api/gametelemetry/models/list_base_response_str.py
accelbyte_py_sdk/api/gametelemetry/models/paged_response_get_namespace_event_response.py
accelbyte_py_sdk/api/gametelemetry/models/paging.py
accelbyte_py_sdk/api/gametelemetry/models/play_time_response.py
accelbyte_py_sdk/api/gametelemetry/models/telemetry_body.py
accelbyte_py_sdk/api/gametelemetry/models/validation_error.py
accelbyte_py_sdk/api/gametelemetry/operations/__init__.py
accelbyte_py_sdk/api/gametelemetry/operations/gametelemetry_operations/__init__.py
accelbyte_py_sdk/api/gametelemetry/operations/gametelemetry_operations/protected_get_playtime__9a0e17.py
accelbyte_py_sdk/api/gametelemetry/operations/gametelemetry_operations/protected_save_events_g_832bbb.py
accelbyte_py_sdk/api/gametelemetry/operations/gametelemetry_operations/protected_update_playti_4b5b85.py
accelbyte_py_sdk/api/gametelemetry/operations/telemetry/__init__.py
accelbyte_py_sdk/api/gametelemetry/operations/telemetry/get_events_game_telemet_b2983d.py
accelbyte_py_sdk/api/gametelemetry/operations/telemetry/get_namespaces_game_tel_1106fd.py
accelbyte_py_sdk/api/gametelemetry/wrappers/__init__.py
accelbyte_py_sdk/api/gametelemetry/wrappers/_gametelemetry_operations.py
accelbyte_py_sdk/api/gametelemetry/wrappers/_telemetry.py
accelbyte_py_sdk_service_gametelemetry-0.21.0.dist-info/METADATA
accelbyte_py_sdk_service_gametelemetry-0.21.0.dist-info/WHEEL
accelbyte_py_sdk_service_gametelemetry-0.21.0.dist-info/top_level.txt
accelbyte_py_sdk_service_gametelemetry-0.21.0.dist-info/RECORD
