Metadata-Version: 2.4
Name: accelbyte-py-sdk-service-gametelemetry
Version: 0.21.0
Summary: AccelByte Python SDK - Analytics Game Telemetry
Requires-Python: >=3.9
Requires-Dist: accelbyte-py-sdk-core
